5790: # Method Name:       post
5791: # Filename:          indicadores\views.py
5792: # Argument count:    2
5793: # Position-only argument count: 0
5794: # Keyword-only arguments: 0
5795: # Number of locals:  30
5796: # Stack size:        17
5797: # Flags:             0x00000003 (NEWLOCALS | OPTIMIZED)
5798: # First Line:        739
5799: # Constants:
5800: #    0: None
5801: #    1: 'indicador'
5802: #    2: 'valor_atual'
5803: #    3: 'unidade'
5804: #    4: 'Geral (Todas as Unidades)'
5805: #    5: 'erro'
5806: #    6: "Campos 'indicador' e 'valor_atual' sÒo obrigat¾rios."
5807: #    7: 400
5808: #    8: ('status',)
5809: #    9: 0
5810: #   10: <Code311 code object normalize_text at 0x1f294e1fdf0, file indicadores\views.py>, line 752
5811: #   11: 'Faturamento SUS'
5812: #   12: 'Garantir o processamento integral da receita de serviþos sob o regime do SUS, auditando as AIHs e APACs para evitar glosas.'
5813: #   13: '═ndice de Glosa Inicial'
5814: #   14: 'Identificar falhas de preenchimento e autorizaþÒo de contas mÚdicas junto Ós operadoras e gestor p·blico.'
5815: #   15: 'Taxa de RecuperaþÒo'
5816: #   16: 'Maximizar a conversÒo de recursos de glosas por meio de contestaþÒo tÚcnica e justificativa clÝnica rßpida.'
5817: #   17: 'EvasÒo de Receita'
5818: #   18: 'Monitorar perdas definitivas para corrigir falhas processuais no faturamento e mitigar impacto na margem EBITDA.'
5819: #   19: 'Pacientes na Fila (Backlog)'
5820: #   20: 'Garantir a fluidez assistencial, otimizando o agendamento de exames e cirurgias eletivas represadas no AGHUse.'
5821: #   21: 'Fila de Espera (Backlog)'
5822: #   22: 'Taxa de OcupaþÒo MÚdia'
5823: #   23: 'Otimizar o giro de leitos das unidades crÝticas e enfermarias para atender Ó demanda de admiss§es do pronto-socorro.'
5824: #   24: 'Taxa de OcupaþÒo'
5825: #   25: 'Taxa de SuspensÒo'
5826: #   26: 'Reduzir o cancelamento de cirurgias programadas por falha de preparo clÝnico ou ociosidade do bloco cir·rgico.'
5827: #   27: 'Taxa de SuspensÒo de Procedimentos'
5828: #   28: 'TMP (PermanÛncia)'
5829: #   29: 'Reduzir a permanÛncia desnecessßria, agilizando desospitalizaþÒo segura e mitigando o risco de infecþ§es secundßrias.'
5830: #   30: 'Densidade de RH'
5831: #   31: 'Dimensionar adequadamente a relaþÒo entre profissionais assistenciais por leito para preservar a seguranþa assistencial.'
5832: #   32: 'Densidade RH'
5833: #   33: 'Score de Risco ClÝnico'
5834: #   34: 'Prevenir incidentes e prever o risco setorial associando dimensionamento de pessoal, absenteÝsmo e ocorrÛncias clÝnicas.'
5835: #   35: 'Taxa IRAS (InfecþÒo)'
5836: #   36: 'Garantir a adesÒo aos protocolos de controle de infecþÒo e higienizaþÒo de leitos nas unidades crÝticas.'
5837: #   37: 'SubstituiþÒo de Leito'
5838: #   38: 'Agilizar o tempo de higienizaþÒo e liberaþÒo do leito ap¾s a alta para diminuir o tempo de espera no pronto-socorro.'
5839: #   39: 'Consumo ┴gua/Energia'
5840: #   40: 'Gerenciar o consumo de recursos naturais e custos fixos na infraestrutura predial hospitalar.'
5841: #   41: 'NPS (SatisfaþÒo)'
5842: #   42: 'Monitorar a fidelidade e a qualidade percebida pelo paciente com foco na melhoria da experiÛncia de internaþÒo.'
5843: #   43: 'Taxa ReinternaþÒo'
5844: #   44: 'Auditar a qualidade clÝnica das altas, reduzindo reinternaþ§es evitßveis nos 30 dias subsequentes.'
5845: #   45: 'Giro de Estoque'
5846: #   46: 'Evitar capital parado garantindo abastecimento contÝnuo de insumos e medicamentos na farmßcia central.'
5847: #   47: 'Custo Total'
5848: #   48: 'Monitorar a distribuiþÒo e gasto total de medicamentos para assegurar o controle orþamentßrio do estoque.'
5849: #   49: 'Erros MedicaþÒo'
5850: #   50: 'Mitigar a ocorrÛncia de eventos adversos na administraþÒo de medicamentos via dupla checagem e barreiras eletr¶nicas.'
5851: #   51: 'Ruptura Estoque'
5852: #   52: 'Evitar a falta de itens essenciais na assistÛncia garantindo compras tempestivas frente Ó variaþÒo de demanda.'
5853: #   53: 'Taxa de Ruptura'
5854: #   54: 'AdesÒo Protocolos'
5855: #   55: 'Monitorar a conformidade do corpo clÝnico com as diretrizes e protocolos institucionais (ex: Sepse, IAM).'
5856: #   56: 'Tempo Prontußrio'
5857: #   57: 'Garantir o fechamento tempestivo do prontußrio pelo mÚdico para acelerar o processo de faturamento das contas.'
5858: #   58: 'AbsenteÝsmo MÚdico'
5859: #   59: 'Reduzir faltas e atrasos na escala mÚdica de plantÒo para evitar sobrecarga de equipe e demora no atendimento.'
5860: #   60: 'AbsenteÝsmo'
5861: #   61: 'Unidades em Risco CrÝtico'
5862: #   62: 'Identificar e priorizar intervenþ§es de lideranþa nas unidades hospitalares que apresentam score de risco clÝnico elevado.'
5863: #   63: 'Ticket MÚdio'
5864: #   64: 'Acompanhar o valor mÚdio faturado por atendimento para analisar o perfil epidemiol¾gico e financeiro das internaþ§es.'
5865: #   65: 'PMR'
5866: #   66: 'Prazo MÚdio de Recebimento: Controlar o ciclo financeiro entre a alta do paciente e a liquidaþÒo das contas pelos convÛnios.'
5867: #   67: 'PMR (Recebimento)'
5868: #   68: 'Volume Especialidade'
5869: #   69: 'Analisar a distribuiþÒo da volumetria assistencial por especialidade mÚdica para subsidiar o planejamento de escalas e capacidade fÝsica.'
5870: #   70: 'EBITDA Operacional'
5871: #   71: 'Garantir a sustentabilidade operacional medindo o resultado financeiro primßrio gerado pelas atividades hospitalares (EBITDA), excluindo impostos e depreciaþ§es.'
5872: #   72: 'Monitorar e auditar as faturas com glosas iniciais aplicadas pelas operadoras de sa·de, buscando maximizar a recuperaþÒo e mitigar perdas definitivas.'
5873: #   73: 'Otimizar a ocupaþÒo fÝsica das salas cir·rgicas, reduzindo o tempo de setup (preparo e limpeza) entre procedimentos consecutivos.'
5874: #   74: 'Avaliar a produtividade e ocupaþÒo operacional de equipamentos de alta complexidade instalados nas salas de exames e blocos.'
5875: #   75: 'Monitorar a proporþÒo de procedimentos programados que foram efetivamente concluÝdos, reduzindo cancelamentos e ociosidade mÚdica.'
5876: #   76: ('GestÒo de Glosas', 'Giro de Sala', 'Produtividade', 'Taxa ConversÒo')
5877: #   77: 'Monitorar a mÚtrica para garantir a conformidade operacional e a eficiÛncia clÝnica e financeira do hospital.'
5878: #   78: <Code311 code object <lambda> at 0x1f294e1ff00, file indicadores\views.py>, line 812
5879: #   79: True
5880: #   80: ('key', 'reverse')
5881: #   81: "VocÛ Ú o Assistente Executivo de InteligÛncia AnalÝtica do Hospital.\nO usußrio estß visualizando o painel de BI e solicitou a explicaþÒo do indicador: '"
5882: #   82: "'.\nA diretriz estratÚgica oficial da nossa instituiþÒo para esta mÚtrica Ú: '"
5883: #   83: "'.\nO valor atualmente registrado em tela Ú: "
5884: #   84: ' (na unidade: '
5885: #   85: ').\n\nSua tarefa Ú retornar uma resposta curta, estruturada em formato markdown para o frontend, contendo exatamente dois parßgrafos:\n1. ### **[Conceito]**: Explique em portuguÛs simples o que este indicador mede e por que ele importa para o hospital baseado na nossa diretriz estratÚgica.\n2. ### **[Anßlise de AþÒo]**: Avalie o valor atual ('
5886: #   86: '). Se for um valor crÝtico (como absenteÝsmo alto, glosa alta ou baixa densidade de RH), alerte o gestor e sugira uma linha de aþÒo corretiva imediata. Seja direto, executivo e profissional.\n'
5887: #   87: 'GEMINI_API_KEY'
5888: #   88: 'OPENAI_API_KEY'
5889: #   89: 'https://generativelanguage.googleapis.com/v1beta/models/gemini-1.5-flash:generateContent?key='
5890: #   90: 'contents'
5891: #   91: 'parts'
5892: #   92: 'text'
5893: #   93: 8
5894: #   94: ('json', 'timeout')
5895: #   95: 200
5896: #   96: 'candidates'
5897: #   97: 'content'
5898: #   98: 'resposta'
5899: #   99: 'https://api.openai.com/v1/chat/completions'
5900: #  100: 'Bearer '
5901: #  101: 'application/json'
5902: #  102: ('Authorization', 'Content-Type')
5903: #  103: 'gpt-4o-mini'
5904: #  104: 'system'
5905: #  105: 'VocÛ Ú o Assistente Executivo de InteligÛncia AnalÝtica do Hospital.'
5906: #  106: ('role', 'content')
5907: #  107: 'user'
5908: #  108: ('model', 'messages')
5909: #  109: ('json', 'headers', 'timeout')
5910: #  110: 'choices'
5911: #  111: 'message'
5912: #  112: 0.0
5913: #  113: 'faturamento'
5914: #  114: 'O **Faturamento SUS** mede o montante financeiro total faturado e homologado sob o regime do SUS no perÝodo. ╔ crÝtico para a sa·de financeira do hospital, pois o SUS representa uma fatia importante da receita operacional, exigindo o controle estrito das AIHs e APACs para evitar glosas administrativas.'
5915: #  115: 'gestao de glosas'
5916: #  116: 'A **GestÒo de Glosas** avalia o andamento das faturas contestadas e o status de recuperaþÒo das glosas aplicadas pelos convÛnios, identificando a eficiÛncia operacional das ßreas de auditoria e faturamento.'
5917: #  117: 'glosa'
5918: #  118: 'O **═ndice de Glosa Inicial** mede o percentual do faturamento total que foi inicialmente rejeitado pelas operadoras ou pelo gestor do SUS devido a inconsistÛncias cadastrais, falhas de autorizaþÒo de contas mÚdicas ou falta de conformidade clÝnica.'
5919: #  119: 'recupera'
5920: #  120: 'A **Taxa de RecuperaþÒo** avalia a eficiÛncia e agilidade da equipe de auditoria e faturamento em contestar e recuperar recursos inicialmente glosados pelas operadoras ou pelo gestor p·blico, minimizando o impacto no fluxo de caixa.'
5921: #  121: 'evas'
5922: #  122: 'A **EvasÒo de Receita** representa as perdas financeiras definitivas decorrentes de glosas nÒo recuperadas no perÝodo. ╔ um indicador vital que impacta diretamente a margem EBITDA e a capacidade de investimento da instituiþÒo.'
5923: #  123: 'backlog'
5924: #  124: "A **Fila de Espera (Backlog)** quantifica o total de pacientes com exames ou cirurgias programadas que se encontram em status 'Agendado' aguardando execuþÒo fÝsica, indicando a pressÒo assistencial do fluxo do AGHUse."
5925: #  125: 'fila'
5926: #  126: 'ocupa'
5927: #  127: 'A **Taxa de OcupaþÒo MÚdia** mede o percentual mÚdio de leitos ou cadeiras ocupados em relaþÒo Ó capacidade mßxima. Ela avalia o aproveitamento dos recursos fÝsicos e Ú fundamental para gerenciar o gargalo de admiss§es hospitalares.'
5928: #  128: 'suspen'
5929: #  129: 'A **Taxa de SuspensÒo de Procedimentos** monitora a proporþÒo de cirurgias ou exames cancelados ap¾s o agendamento oficial. Reflete falhas no preparo clÝnico prÚ-operat¾rio dos pacientes ou na coordenaþÒo das salas de cirurgia.'
5930: #  130: 'tmp'
5931: #  131: 'O **Tempo MÚdio de PermanÛncia (TMP)** monitora o n·mero mÚdio de dias que os pacientes passam internados. ╔ um indicador da eficiÛncia clÝnica, no qual permanÛncias prolongadas aumentam os custos fixos e os riscos de infecþÒo.'
5932: #  132: 'densidade'
5933: #  133: 'A **Densidade de Recursos Humanos** mede a proporþÒo mÚdia de profissionais assistenciais (como enfermeiros e tÚcnicos) ativos por leito instalado, sendo uma mÚtrica chave de seguranþa do paciente contra fadiga e sobrecarga.'
5934: #  134: 'risco'
5935: #  135: 'O **Score de Risco ClÝnico** Ú uma mÚtrica preditiva que unifica absenteÝsmo mÚdico, densidade de RH, e ocorrÛncias de erros/infecþ§es por setor para sinalizar preventivamente quais ßreas necessitam de intervenþÒo urgente.'
5936: #  136: 'iras'
5937: #  137: 'A **Taxa IRAS** avalia o percentual de Infecþ§es Relacionadas Ó AssistÛncia Ó Sa·de sobre o total de saÝdas, funcionando como o principal term¶metro de conformidade e seguranþa higiÛnica e clÝnica da instituiþÒo.'
5938: #  138: 'substitui'
5939: #  139: 'O tempo de **SubstituiþÒo de Leito** monitora o intervalo entre a desocupaþÒo do leito por alta e a sua disponibilidade real para o pr¾ximo paciente, medindo a eficiÛncia operacional da hotelaria.'
5940: #  140: 'nps'
5941: #  141: 'O **NPS (Net Promoter Score)** mede a satisfaþÒo e fidelidade do paciente ap¾s o atendimento hospitalar, indicando a percepþÒo humana sobre o cuidado recebido e a experiÛncia geral na instituiþÒo.'
5942: #  142: 'reinterna'
5943: #  143: 'A **Taxa de ReinternaþÒo** monitora o percentual de pacientes que voltam a ser hospitalizados em atÚ 30 dias pela mesma causa. Altos Ýndices apontam para problemas na eficßcia do tratamento ou na qualidade do processo de alta.'
5944: #  144: 'consumo'
5945: #  145: 'O **Consumo ┴gua/Energia** monitora a eficiÛncia ecol¾gica e financeira da infraestrutura hospitalar, visando otimizar custos operacionais de ßgua e energia elÚtrica sem comprometer a operaþÒo e seguranþa clÝnica.'
5946: #  146: 'O **Giro de Estoque** monitora a frequÛncia com que o estoque de medicamentos da farmßcia central se renova. Altos giros indicam boa gestÒo de capital de giro, enquanto baixos giros sugerem excesso de itens parados e risco de vencimento.'
5947: #  147: 'O **Giro de Sala** mede a duraþÒo mÚdia de ocupaþÒo das salas cir·rgicas, englobando o setup de anestesia, o tempo cir·rgico e o intervalo de limpeza fÝsica da sala pela enfermagem.'
5948: #  148: 'O **Custo Total** de medicamentos monitora o consumo financeiro acumulado das dispensaþ§es da farmßcia, servindo de term¶metro para controle do orþamento de insumos da instituiþÒo.'
5949: #  149: 'O indicador de **Erros MedicaþÒo** monitora incidentes na prescriþÒo, dispensaþÒo ou administraþÒo de medicamentos, servindo como term¶metro primßrio de seguranþa assistencial nas unidades.'
5950: #  150: 'A **Ruptura Estoque** mede a ocorrÛncia de falta de itens assistenciais crÝticos na farmßcia quando solicitados pelas equipes. Altos Ýndices indicam falhas de suprimentos que comprometem diretamente a assistÛncia.'
5951: #  151: 'A **AdesÒo Protocolos** clÝnicos avalia a conformidade das condutas mÚdicas em relaþÒo Ós diretrizes oficiais adotadas no hospital (como os protocolos de Sepse e AVC), assegurando um cuidado homogÛneo e seguro.'
5952: #  152: 'O **Tempo Prontußrio** mede a mÚdia de minutos ou horas que os mÚdicos levam para fechar o prontußrio do paciente ap¾s o atendimento. Fechamentos tardios atrasam o faturamento da conta do SUS e operadoras.'
5953: #  153: 'O **AbsenteÝsmo MÚdico** monitora o Ýndice de faltas e atrasos na escala de plant§es, refletindo o grau de aderÛncia dos profissionais Ós escalas fÝsicas homologadas.'
5954: #  154: 'O **Ticket MÚdio** avalia o valor financeiro mÚdio faturado por atendimento ou internaþÒo, auxiliando a gerÛncia na anßlise da complexidade dos casos assistidos no hospital.'
5955: #  155: 'O **PMR (Prazo MÚdio de Recebimento)** monitora o intervalo de dias entre a alta clÝnica do paciente e o efetivo pagamento da conta faturada pelos convÛnios e SUS.'
5956: #  156: 'O **EBITDA Operacional** mede a lucratividade operacional do hospital antes de juros, impostos, depreciaþÒo e amortizaþÒo, demonstrando a capacidade de geraþÒo de caixa das atividades essenciais.'
5957: #  157: 'O **Volume Especialidade** quantifica a distribuiþÒo dos atendimentos e procedimentos por especialidade mÚdica, servindo para planejar a escala mÚdica e a capacidade instalada.'
5958: #  158: 'A **Produtividade por Equipamento** mede o volume de procedimentos e exames diagn¾sticos realizados nas mßquinas de alta complexidade mÚdica, otimizando o uso dos ativos.'
5959: #  159: 'A **Taxa ConversÒo** indica a proporþÒo de cirurgias ou procedimentos de fato realizados em relaþÒo aos agendamentos solicitados, auxiliando a reduzir suspens§es e ociosidade de equipes.'
5960: #  160: ('giro de estoque', 'giro de sala', 'giro', 'custo', 'erro', 'ruptura', 'ades', 'prontu', 'absen', 'ticket', 'pmr', 'ebitda', 'volume', 'produtividade', 'conversao')
5961: #  161: 'O valor atual de **{valor_atual}** na unidade **{unidade}** indica a receita processada. Sugere-se intensificar a auditoria preventiva em contas de alta complexidade (como cirurgias) antes do fechamento do lote para assegurar conformidade total e evitar prejuÝzos.'
5962: #  162: 'O andamento da gestÒo de glosas de **{valor_atual}** na unidade **{unidade}** aponta para oportunidades de conciliaþÒo. Sugere-se priorizar recursos junto Ós maiores operadoras parceiras e padronizar justificativas clÝnicas.'
5963: #  163: 'O Ýndice atual de **{valor_atual}** na unidade **{unidade}** estß em patamar considerßvel. Recomenda-se realizar um treinamento com a recepþÒo para reduzir erros cadastrais e revisar o fluxo de prÚ-autorizaþ§es junto Ós operadoras.'
5964: #  164: 'A taxa de recuperaþÒo de **{valor_atual}** na unidade **{unidade}** reflete a eficßcia dos recursos. Para maximizar esse indicador, sugere-se a padronizaþÒo das justificativas clÝnicas e a automatizaþÒo da conciliaþÒo de glosas.'
5965: #  165: 'O valor de **{valor_atual}** na unidade **{unidade}** representa perda de receita definitiva. Alerta-se a gestÒo para implementar travas no prontußrio eletr¶nico que impeþam a alta administrativa sem que todas as guias de cobranþa estejam validadas.'
5966: #  166: 'A fila atual de **{valor_atual}** na unidade **{unidade}** representa um gargalo. Recomenda-se otimizar a escala das salas de cirurgia/exames e priorizar procedimentos que dependam de equipamentos com maior ociosidade operacional.'
5967: #  167: 'A ocupaþÒo atual de **{valor_atual}** na unidade **{unidade}** estß pr¾xima da saturaþÒo. Recomenda-se agilizar as altas seguras pela manhÒ e implantar um painel de monitoramento do giro de leitos para diminuir o tempo de espera no pronto-socorro.'
5968: #  168: 'A taxa de suspensÒo de **{valor_atual}** na unidade **{unidade}** Ú crÝtica. Sugere-se implementar um contato telef¶nico de confirmaþÒo com o paciente 24h antes do procedimento para garantir o preparo prÚ-operat¾rio adequado e reduzir absenteÝsmo.'
5969: #  169: 'O TMP atual de **{valor_atual}** na unidade **{unidade}** exige atenþÒo. Recomenda-se auditar casos de longa permanÛncia (acima de 15 dias) e criar uma comissÒo multidisciplinar para agilizar desospitalizaþ§es seguras.'
5970: #  170: 'A densidade atual de **{valor_atual}** na unidade **{unidade}** aponta para sobrecarga de pessoal. Recomenda-se remanejar tÚcnicos e enfermeiros temporariamente para este setor para evitar a fadiga da equipe e mitigar o risco de erros assistenciais.'
5971: #  171: 'O score atual de **{valor_atual}** na unidade **{unidade}** Ú classificado como crÝtico. Recomenda-se intervenþÒo preventiva imediata da lideranþa com auditoria volante e redimensionamento imediato das escalas de pessoal assistencial no setor.'
5972: #  172: 'A taxa de infecþ§es de **{valor_atual}** na unidade **{unidade}** demanda reforþo. Sugere-se intensificar a fiscalizaþÒo da lavagem de mÒos e auditar o cumprimento estrito das rotinas de desinfecþÒo de leitos da hotelaria.'
5973: #  173: 'O tempo atual de **{valor_atual}** na unidade **{unidade}** estß acima do ideal (120 min). Recomenda-se criar alertas em tempo real para a equipe de limpeza assim que o paciente desocupe o leito, agilizando o fluxo.'
5974: #  174: 'O NPS atual de **{valor_atual}** reflete a experiÛncia do paciente. Recomenda-se mapear os principais detratores atravÚs de ligaþ§es p¾s-alta e agir nos gargalos de hotelaria e alimentaþÒo relatados.'
5975: #  175: 'A taxa de reinternaþÒo atual de **{valor_atual}** na unidade **{unidade}** exige revisÒo. Sugere-se implantar um acompanhamento telef¶nico p¾s-alta de 48 horas para tirar d·vidas de prescriþÒo e mitigar retornos evitßveis.'
5976: #  176: 'O consumo registrado de **{valor_atual}** na unidade **{unidade}** indica o nÝvel de utilizaþÒo de recursos prediais. Recomenda-se realizar uma auditoria de desperdÝcio e checar contratos de demanda de energia para otimizar os custos fixos.'
5977: #  177: 'O giro atual de **{valor_atual}** na unidade **{unidade}** aponta para a velocidade de escoamento. Recomenda-se ajustar a curva ABC de compras e calibrar os estoques mÝnimos de medicamentos de alto custo para evitar vencimentos.'
5978: #  178: 'O giro de sala atual de **{valor_atual}** na unidade **{unidade}** exige otimizaþÒo. Recomenda-se paralelizar a limpeza fÝsica com o preparo anestÚsico da pr¾xima cirurgia em sala contÝgua para reduzir a ociosidade do bloco.'
5979: #  179: 'O custo total acumulado de **{valor_atual}** na unidade **{unidade}** exige conciliaþÒo orþamentßria. Recomenda-se auditar prescriþ§es de alta variabilidade clÝnica e padronizar o uso de genÚricos de alta eficßcia.'
5980: #  180: 'O volume atual de **{valor_atual}** erros de medicaþÒo na unidade **{unidade}** exige revisÒo imediata. Recomenda-se reforþar a dupla checagem na enfermagem e revisar a clareza da prescriþÒo no prontußrio eletr¶nico.'
5981: #  181: 'A taxa de ruptura de **{valor_atual}** na unidade **{unidade}** estß elevada. Sugere-se adiantar os pedidos de compra junto aos fornecedores homologados e verificar eventuais atrasos logÝsticos na entrega.'
5982: #  182: 'A taxa de adesÒo atual de **{valor_atual}** na unidade **{unidade}** indica a conformidade clÝnica. Sugere-se promover sess§es de educaþÒo continuada com a equipe mÚdica e simplificar as ferramentas de registro no sistema.'
5983: #  183: 'O tempo de fechamento de **{valor_atual}** na unidade **{unidade}** estß acima do ideal. Recomenda-se disparar alertas automßticos aos mÚdicos com pendÛncias acima de 24 horas para evitar glosas por perda de prazo.'
5984: #  184: 'O absenteÝsmo atual de **{valor_atual}** na unidade **{unidade}** estß crÝtico. Recomenda-se acionar o banco de mÚdicos de reserva para cobrir escalas e realizar entrevista de feedback com os profissionais com maior recorrÛncia de faltas.'
5985: #  185: 'O ticket mÚdio atual de **{valor_atual}** na unidade **{unidade}** reflete a receita por paciente. Sugere-se auditar o registro correto de procedimentos nas contas para garantir que todo o cuidado prestado esteja sendo faturado.'
5986: #  186: 'O PMR atual de **{valor_atual}** na unidade **{unidade}** impacta o fluxo de caixa. Recomenda-se revisar as glosas recursais pendentes e estreitar a negociaþÒo com as operadoras para acelerar o ciclo de contas a receber.'
5987: #  187: 'O EBITDA operacional atual de **{valor_atual}** na unidade **{unidade}** indica a capacidade de autofinanciamento. Sugere-se revisar os custos operacionais de insumos farmacol¾gicos e taxa de glosa para melhorar a margem operacional lÝquida.'
5988: #  188: 'O volume assistencial atual de **{valor_atual}** na unidade **{unidade}** deve ser avaliado contra a capacidade instalada. Recomenda-se redimensionar escalas mÚdicas para especialidades com maior tempo mÚdio de fila.'
5989: #  189: 'A produtividade registrada de **{valor_atual}** na unidade **{unidade}** exige anßlise de ociosidade tÚcnica. Sugere-se agendar exames eletivos em horßrios alternativos para otimizar o retorno operacional do ativo fÝsico.'
5990: #  190: 'A taxa de conversÒo atual de **{valor_atual}** na unidade **{unidade}** indica a estabilidade da agenda. Recomenda-se implantar check-in cir·rgico digital 48h antes e revisar os tempos de liberaþÒo de leitos cir·rgicos.'
5991: #  191: <Code311 code object <lambda> at 0x1f2950bc9e0, file indicadores\views.py>, line 942
5992: #  192: ('valor_atual', 'unidade')
5993: #  193: '### **[Conceito]**\n'
5994: #  194: '\n\n### **[Anßlise de AþÒo]**\n'
5995: # Names:
5996: #    0: data
5997: #    1: get
5998: #    2: response
5999: #    3: Response
6000: #    4: unicodedata
6001: #    5: sorted
6002: #    6: items
6003: #    7: os
6004: #    8: environ
6005: #    9: requests
6006: #   10: post
6007: #   11: status_code
6008: #   12: json
6009: #   13: Exception
6010: #   14: re
6011: #   15: keys
6012: #   16: format
6013: # Varnames:
6014: #	self, request, indicador, valor_atual, unidade, indicador_norm, kpi_directives, definicao_institucional, sorted_directives, k, v, k_norm, system_prompt, gemini_key, openai_key, requests, url_api, payload, res, text_response, headers, re, val_num, p1_concepts, p2_actions, key_match, sorted_keys, concept_p, action_p, response_markdown
6015: # Positional arguments:
6016: #	self, request
6017: # Local variables:
6018: #    2: indicador
6019: #    3: valor_atual
6020: #    4: unidade
6021: #    5: indicador_norm
6022: #    6: kpi_directives
6023: #    7: definicao_institucional
6024: #    8: sorted_directives
6025: #    9: k
6026: #   10: v
6027: #   11: k_norm
6028: #   12: system_prompt
6029: #   13: gemini_key
6030: #   14: openai_key
6031: #   15: requests
6032: #   16: url_api
6033: #   17: payload
6034: #   18: res
6035: #   19: text_response
6036: #   20: headers
6037: #   21: re
6038: #   22: val_num
6039: #   23: p1_concepts
6040: #   24: p2_actions
6041: #   25: key_match
6042: #   26: sorted_keys
6043: #   27: concept_p
6044: #   28: action_p
6045: #   29: response_markdown
6046: # Cell variables:
6047: #    0: normalize_text
6048: #    1: unicodedata
6049:                0 MAKE_CELL            (normalize_text)
6050:                2 MAKE_CELL            (unicodedata)
6051: 
6052: 739:           4 RESUME               0
6053: 
6054: 740:           6 LOAD_FAST            (request)
6055:                8 LOAD_ATTR            (data)
6056:               28 LOAD_ATTR            (NULL|self + get)
6057:               48 LOAD_CONST           ("indicador")
6058:               50 CALL                 1
6059:               58 STORE_FAST           (indicador)
6060: 
6061: 741:          60 LOAD_FAST            (request)
6062:               62 LOAD_ATTR            (data)
6063:               82 LOAD_ATTR            (NULL|self + get)
6064:              102 LOAD_CONST           ("valor_atual")
6065:              104 CALL                 1
6066:              112 STORE_FAST           (valor_atual)
6067: 
6068: 742:         114 LOAD_FAST            (request)
6069:              116 LOAD_ATTR            (data)
6070:              136 LOAD_ATTR            (NULL|self + get)
6071:              156 LOAD_CONST           ("unidade")
6072:              158 CALL                 1
6073:              166 COPY                 1
6074:              168 POP_JUMP_IF_TRUE     (to 174)
6075:              170 POP_TOP
6076:              172 LOAD_CONST           ("Geral (Todas as Unidades)")
6077:          >>  174 STORE_FAST           (unidade)
6078: 
6079: 744:         176 LOAD_FAST            (indicador)
6080:              178 POP_JUMP_IF_FALSE    (to 184)
6081:              180 LOAD_FAST            (valor_atual)
6082:              182 POP_JUMP_IF_TRUE     (to 234)
6083: 
6084: 745:     >>  184 LOAD_GLOBAL          (NULL + response)
6085:              194 LOAD_ATTR            (Response)
6086: 
6087: 746:         214 LOAD_CONST           ("erro")
6088:              216 LOAD_CONST           ("Campos 'indicador' e 'valor_atual' sÒo obrigat¾rios.")
6089:              218 BUILD_MAP            1
6090: 
6091: 747:         220 LOAD_CONST           (400)
6092: 
6093: 745:         222 KW_NAMES             (('status',))
6094:              224 CALL                 2
6095:              232 RETURN_VALUE
6096: 
6097: 750:     >>  234 LOAD_CONST           (0)
6098:              236 LOAD_CONST           (None)
6099:              238 IMPORT_NAME          (unicodedata)
6100:              240 STORE_DEREF          (unicodedata)
6101: 
6102: 752:         242 LOAD_CLOSURE         (unicodedata)
6103:              244 BUILD_TUPLE          1
6104:              246 LOAD_CONST           (<Code311 code object normalize_text at 0x1f294e1fdf0, file indicadores\views.py>, line 752)
6105:              248 MAKE_FUNCTION        (closure)
6106:              250 STORE_DEREF          (normalize_text)
6107: 
6108: 765:         252 PUSH_NULL
6109:              254 LOAD_DEREF           (normalize_text)
6110:              256 LOAD_FAST            (indicador)
6111:              258 CALL                 1
6112:              266 STORE_FAST           (indicador_norm)
6113: 
6114: 768:         268 BUILD_MAP            0
6115: 
6116: 769:         270 LOAD_CONST           ("Faturamento SUS")
6117:              272 LOAD_CONST           ("Garantir o processamento integral da receita de serviþos sob o regime do SUS, auditando as AIHs e APACs para evitar glosas.")
6118: 
6119: 768:         274 MAP_ADD              1
6120: 
6121: 770:         276 LOAD_CONST           ("═ndice de Glosa Inicial")
6122:              278 LOAD_CONST           ("Identificar falhas de preenchimento e autorizaþÒo de contas mÚdicas junto Ós operadoras e gestor p·blico.")
6123: 
6124: 768:         280 MAP_ADD              1
6125: 
6126: 771:         282 LOAD_CONST           ("Taxa de RecuperaþÒo")
6127:              284 LOAD_CONST           ("Maximizar a conversÒo de recursos de glosas por meio de contestaþÒo tÚcnica e justificativa clÝnica rßpida.")
6128: 
6129: 768:         286 MAP_ADD              1
6130: 
6131: 772:         288 LOAD_CONST           ("EvasÒo de Receita")
6132:              290 LOAD_CONST           ("Monitorar perdas definitivas para corrigir falhas processuais no faturamento e mitigar impacto na margem EBITDA.")
6133: 
6134: 768:         292 MAP_ADD              1
6135: 
6136: 773:         294 LOAD_CONST           ("Pacientes na Fila (Backlog)")
6137:              296 LOAD_CONST           ("Garantir a fluidez assistencial, otimizando o agendamento de exames e cirurgias eletivas represadas no AGHUse.")
6138: 
6139: 768:         298 MAP_ADD              1
6140: 
6141: 774:         300 LOAD_CONST           ("Fila de Espera (Backlog)")
6142:              302 LOAD_CONST           ("Garantir a fluidez assistencial, otimizando o agendamento de exames e cirurgias eletivas represadas no AGHUse.")
6143: 
6144: 768:         304 MAP_ADD              1
6145: 
6146: 775:         306 LOAD_CONST           ("Taxa de OcupaþÒo MÚdia")
6147:              308 LOAD_CONST           ("Otimizar o giro de leitos das unidades crÝticas e enfermarias para atender Ó demanda de admiss§es do pronto-socorro.")
6148: 
6149: 768:         310 MAP_ADD              1
6150: 
6151: 776:         312 LOAD_CONST           ("Taxa de OcupaþÒo")
6152:              314 LOAD_CONST           ("Otimizar o giro de leitos das unidades crÝticas e enfermarias para atender Ó demanda de admiss§es do pronto-socorro.")
6153: 
6154: 768:         316 MAP_ADD              1
6155: 
6156: 777:         318 LOAD_CONST           ("Taxa de SuspensÒo")
6157:              320 LOAD_CONST           ("Reduzir o cancelamento de cirurgias programadas por falha de preparo clÝnico ou ociosidade do bloco cir·rgico.")
6158: 
6159: 768:         322 MAP_ADD              1
6160: 
6161: 778:         324 LOAD_CONST           ("Taxa de SuspensÒo de Procedimentos")
6162:              326 LOAD_CONST           ("Reduzir o cancelamento de cirurgias programadas por falha de preparo clÝnico ou ociosidade do bloco cir·rgico.")
6163: 
6164: 768:         328 MAP_ADD              1
6165: 
6166: 779:         330 LOAD_CONST           ("TMP (PermanÛncia)")
6167:              332 LOAD_CONST           ("Reduzir a permanÛncia desnecessßria, agilizando desospitalizaþÒo segura e mitigando o risco de infecþ§es secundßrias.")
6168: 
6169: 768:         334 MAP_ADD              1
6170: 
6171: 780:         336 LOAD_CONST           ("Densidade de RH")
6172:              338 LOAD_CONST           ("Dimensionar adequadamente a relaþÒo entre profissionais assistenciais por leito para preservar a seguranþa assistencial.")
6173: 
6174: 768:         340 MAP_ADD              1
6175: 
6176: 781:         342 LOAD_CONST           ("Densidade RH")
6177:              344 LOAD_CONST           ("Dimensionar adequadamente a relaþÒo entre profissionais assistenciais por leito para preservar a seguranþa assistencial.")
6178: 
6179: 768:         346 MAP_ADD              1
6180: 
6181: 782:         348 LOAD_CONST           ("Score de Risco ClÝnico")
6182:              350 LOAD_CONST           ("Prevenir incidentes e prever o risco setorial associando dimensionamento de pessoal, absenteÝsmo e ocorrÛncias clÝnicas.")
6183: 
6184: 768:         352 MAP_ADD              1
6185: 
6186: 783:         354 LOAD_CONST           ("Taxa IRAS (InfecþÒo)")
6187:              356 LOAD_CONST           ("Garantir a adesÒo aos protocolos de controle de infecþÒo e higienizaþÒo de leitos nas unidades crÝticas.")
6188: 
6189: 768:         358 MAP_ADD              1
6190: 
6191: 784:         360 LOAD_CONST           ("SubstituiþÒo de Leito")
6192:              362 LOAD_CONST           ("Agilizar o tempo de higienizaþÒo e liberaþÒo do leito ap¾s a alta para diminuir o tempo de espera no pronto-socorro.")
6193: 
6194: 768:         364 MAP_ADD              1
6195: 
6196: 785:         366 LOAD_CONST           ("Consumo ┴gua/Energia")
6197:              368 LOAD_CONST           ("Gerenciar o consumo de recursos naturais e custos fixos na infraestrutura predial hospitalar.")
6198: 
6199: 768:         370 MAP_ADD              1
6200:              372 BUILD_MAP            0
6201: 
6202: 786:         374 LOAD_CONST           ("NPS (SatisfaþÒo)")
6203:              376 LOAD_CONST           ("Monitorar a fidelidade e a qualidade percebida pelo paciente com foco na melhoria da experiÛncia de internaþÒo.")
6204: 
6205: 768:         378 MAP_ADD              1
6206: 
6207: 787:         380 LOAD_CONST           ("Taxa ReinternaþÒo")
6208:              382 LOAD_CONST           ("Auditar a qualidade clÝnica das altas, reduzindo reinternaþ§es evitßveis nos 30 dias subsequentes.")
6209: 
6210: 768:         384 MAP_ADD              1
6211: 
6212: 788:         386 LOAD_CONST           ("Giro de Estoque")
6213:              388 LOAD_CONST           ("Evitar capital parado garantindo abastecimento contÝnuo de insumos e medicamentos na farmßcia central.")
6214: 
6215: 768:         390 MAP_ADD              1
6216: 
6217: 789:         392 LOAD_CONST           ("Custo Total")
6218:              394 LOAD_CONST           ("Monitorar a distribuiþÒo e gasto total de medicamentos para assegurar o controle orþamentßrio do estoque.")
6219: 
6220: 768:         396 MAP_ADD              1
6221: 
6222: 790:         398 LOAD_CONST           ("Erros MedicaþÒo")
6223:              400 LOAD_CONST           ("Mitigar a ocorrÛncia de eventos adversos na administraþÒo de medicamentos via dupla checagem e barreiras eletr¶nicas.")
6224: 
6225: 768:         402 MAP_ADD              1
6226: 
6227: 791:         404 LOAD_CONST           ("Ruptura Estoque")
6228:              406 LOAD_CONST           ("Evitar a falta de itens essenciais na assistÛncia garantindo compras tempestivas frente Ó variaþÒo de demanda.")
6229: 
6230: 768:         408 MAP_ADD              1
6231: 
6232: 792:         410 LOAD_CONST           ("Taxa de Ruptura")
6233:              412 LOAD_CONST           ("Evitar a falta de itens essenciais na assistÛncia garantindo compras tempestivas frente Ó variaþÒo de demanda.")
6234: 
6235: 768:         414 MAP_ADD              1
6236: 
6237: 793:         416 LOAD_CONST           ("AdesÒo Protocolos")
6238:              418 LOAD_CONST           ("Monitorar a conformidade do corpo clÝnico com as diretrizes e protocolos institucionais (ex: Sepse, IAM).")
6239: 
6240: 768:         420 MAP_ADD              1
6241: 
6242: 794:         422 LOAD_CONST           ("Tempo Prontußrio")
6243:              424 LOAD_CONST           ("Garantir o fechamento tempestivo do prontußrio pelo mÚdico para acelerar o processo de faturamento das contas.")
6244: 
6245: 768:         426 MAP_ADD              1
6246: 
6247: 795:         428 LOAD_CONST           ("AbsenteÝsmo MÚdico")
6248:              430 LOAD_CONST           ("Reduzir faltas e atrasos na escala mÚdica de plantÒo para evitar sobrecarga de equipe e demora no atendimento.")
6249: 
6250: 768:         432 MAP_ADD              1
6251: 
6252: 796:         434 LOAD_CONST           ("AbsenteÝsmo")
6253:              436 LOAD_CONST           ("Reduzir faltas e atrasos na escala mÚdica de plantÒo para evitar sobrecarga de equipe e demora no atendimento.")
6254: 
6255: 768:         438 MAP_ADD              1
6256: 
6257: 797:         440 LOAD_CONST           ("Unidades em Risco CrÝtico")
6258:              442 LOAD_CONST           ("Identificar e priorizar intervenþ§es de lideranþa nas unidades hospitalares que apresentam score de risco clÝnico elevado.")
6259: 
6260: 768:         444 MAP_ADD              1
6261: 
6262: 798:         446 LOAD_CONST           ("Ticket MÚdio")
6263:              448 LOAD_CONST           ("Acompanhar o valor mÚdio faturado por atendimento para analisar o perfil epidemiol¾gico e financeiro das internaþ§es.")
6264: 
6265: 768:         450 MAP_ADD              1
6266: 
6267: 799:         452 LOAD_CONST           ("PMR")
6268:              454 LOAD_CONST           ("Prazo MÚdio de Recebimento: Controlar o ciclo financeiro entre a alta do paciente e a liquidaþÒo das contas pelos convÛnios.")
6269: 
6270: 768:         456 MAP_ADD              1
6271: 
6272: 800:         458 LOAD_CONST           ("PMR (Recebimento)")
6273:              460 LOAD_CONST           ("Prazo MÚdio de Recebimento: Controlar o ciclo financeiro entre a alta do paciente e a liquidaþÒo das contas pelos convÛnios.")
6274: 
6275: 768:         462 MAP_ADD              1
6276: 
6277: 801:         464 LOAD_CONST           ("Volume Especialidade")
6278:              466 LOAD_CONST           ("Analisar a distribuiþÒo da volumetria assistencial por especialidade mÚdica para subsidiar o planejamento de escalas e capacidade fÝsica.")
6279: 
6280: 768:         468 MAP_ADD              1
6281: 
6282: 802:         470 LOAD_CONST           ("EBITDA Operacional")
6283:              472 LOAD_CONST           ("Garantir a sustentabilidade operacional medindo o resultado financeiro primßrio gerado pelas atividades hospitalares (EBITDA), excluindo impostos e depreciaþ§es.")
6284: 
6285: 768:         474 MAP_ADD              1
6286:              476 DICT_UPDATE          1
6287: 
6288: 803:         478 LOAD_CONST           ("Monitorar e auditar as faturas com glosas iniciais aplicadas pelas operadoras de sa·de, buscando maximizar a recuperaþÒo e mitigar perdas definitivas.")
6289: 
6290: 804:         480 LOAD_CONST           ("Otimizar a ocupaþÒo fÝsica das salas cir·rgicas, reduzindo o tempo de setup (preparo e limpeza) entre procedimentos consecutivos.")
6291: 
6292: 805:         482 LOAD_CONST           ("Avaliar a produtividade e ocupaþÒo operacional de equipamentos de alta complexidade instalados nas salas de exames e blocos.")
6293: 
6294: 806:         484 LOAD_CONST           ("Monitorar a proporþÒo de procedimentos programados que foram efetivamente concluÝdos, reduzindo cancelamentos e ociosidade mÚdica.")
6295: 
6296: 768:         486 LOAD_CONST           (('GestÒo de Glosas', 'Giro de Sala', 'Produtividade', 'Taxa ConversÒo'))
6297:              488 BUILD_CONST_KEY_MAP  4
6298:              490 DICT_UPDATE          1
6299:              492 STORE_FAST           (kpi_directives)
6300: 
6301: 809:         494 LOAD_CONST           ("Monitorar a mÚtrica para garantir a conformidade operacional e a eficiÛncia clÝnica e financeira do hospital.")
6302:              496 STORE_FAST           (definicao_institucional)
6303: 
6304: 812:         498 LOAD_GLOBAL          (NULL + sorted)
6305:              508 LOAD_FAST            (kpi_directives)
6306:              510 LOAD_ATTR            (NULL|self + items)
6307:              530 CALL                 0
6308:              538 LOAD_CLOSURE         (normalize_text)
6309:              540 BUILD_TUPLE          1
6310:              542 LOAD_CONST           (<Code311 code object <lambda> at 0x1f294e1ff00, file indicadores\views.py>, line 812)
6311:              544 MAKE_FUNCTION        (closure)
6312:              546 LOAD_CONST           (True)
6313:              548 KW_NAMES             (('key', 'reverse'))
6314:              550 CALL                 3
6315:              558 STORE_FAST           (sorted_directives)
6316: 
6317: 813:         560 LOAD_FAST            (sorted_directives)
6318:              562 GET_ITER
6319:              564 FOR_ITER             (to 618)
6320:              568 UNPACK_SEQUENCE      2
6321:              572 STORE_FAST           (k)
6322:              574 STORE_FAST           (v)
6323: 
6324: 814:         576 PUSH_NULL
6325:              578 LOAD_DEREF           (normalize_text)
6326:              580 LOAD_FAST            (k)
6327:              582 CALL                 1
6328:              590 STORE_FAST           (k_norm)
6329: 
6330: 815:         592 LOAD_FAST            (k_norm)
6331:              594 LOAD_FAST            (indicador_norm)
6332:              596 CONTAINS_OP          (in)
6333:              598 POP_JUMP_IF_TRUE     (to 610)
6334:              600 LOAD_FAST            (indicador_norm)
6335:              602 LOAD_FAST            (k_norm)
6336:              604 CONTAINS_OP          (in)
6337:              606 POP_JUMP_IF_TRUE     (to 610)
6338:              608 JUMP_BACKWARD        (to 564)
6339: 
6340: 816:     >>  610 LOAD_FAST            (v)
6341:              612 STORE_FAST           (definicao_institucional)
6342: 
6343: 817:         614 POP_TOP
6344:          >>  616 JUMP_FORWARD         (to 620)
6345: 
6346: 813:         618 END_FOR
6347: 
6348: 819:     >>  620 LOAD_CONST           ("VocÛ Ú o Assistente Executivo de InteligÛncia AnalÝtica do Hospital.\nO usußrio estß visualizando o painel de BI e solicitou a explicaþÒo do indicador: '")
6349: 
6350: 820:         622 LOAD_FAST            (indicador)
6351:              624 FORMAT_VALUE         0
6352:              626 LOAD_CONST           ("'.\nA diretriz estratÚgica oficial da nossa instituiþÒo para esta mÚtrica Ú: '")
6353: 
6354: 821:         628 LOAD_FAST            (definicao_institucional)
6355:              630 FORMAT_VALUE         0
6356:              632 LOAD_CONST           ("'.\nO valor atualmente registrado em tela Ú: ")
6357: 
6358: 822:         634 LOAD_FAST            (valor_atual)
6359:              636 FORMAT_VALUE         0
6360:              638 LOAD_CONST           (" (na unidade: ")
6361:              640 LOAD_FAST            (unidade)
6362:              642 FORMAT_VALUE         0
6363:              644 LOAD_CONST           (").\n\nSua tarefa Ú retornar uma resposta curta, estruturada em formato markdown para o frontend, contendo exatamente dois parßgrafos:\n1. ### **[Conceito]**: Explique em portuguÛs simples o que este indicador mede e por que ele importa para o hospital baseado na nossa diretriz estratÚgica.\n2. ### **[Anßlise de AþÒo]**: Avalie o valor atual (")
6364: 
6365: 826:         646 LOAD_FAST            (valor_atual)
6366:              648 FORMAT_VALUE         0
6367:              650 LOAD_CONST           ("). Se for um valor crÝtico (como absenteÝsmo alto, glosa alta ou baixa densidade de RH), alerte o gestor e sugira uma linha de aþÒo corretiva imediata. Seja direto, executivo e profissional.\n")
6368: 
6369: 819:         652 BUILD_STRING         11
6370:              654 STORE_FAST           (system_prompt)
6371: 
6372: 829:     >>  656 LOAD_GLOBAL          (os)
6373:              666 LOAD_ATTR            (environ)
6374:              686 LOAD_ATTR            (NULL|self + get)
6375:              706 LOAD_CONST           ("GEMINI_API_KEY")
6376:              708 CALL                 1
6377:              716 STORE_FAST           (gemini_key)
6378: 
6379: 830:         718 LOAD_GLOBAL          (os)
6380:              728 LOAD_ATTR            (environ)
6381:              748 LOAD_ATTR            (NULL|self + get)
6382:              768 LOAD_CONST           ("OPENAI_API_KEY")
6383:              770 CALL                 1
6384:              778 STORE_FAST           (openai_key)
6385: 
6386: 832:         780 LOAD_FAST            (gemini_key)
6387:              782 POP_JUMP_IF_FALSE    (to 1010)
6388: 
6389: 833:         784 LOAD_CONST           (0)
6390:              786 LOAD_CONST           (None)
6391:              788 IMPORT_NAME          (requests)
6392:              790 STORE_FAST           (requests)
6393: 
6394: 834:         792 NOP
6395: 
6396: 835:         794 LOAD_CONST           ("https://generativelanguage.googleapis.com/v1beta/models/gemini-1.5-flash:generateContent?key=")
6397:              796 LOAD_FAST            (gemini_key)
6398:              798 FORMAT_VALUE         0
6399:              800 BUILD_STRING         2
6400:              802 STORE_FAST           (url_api)
6401: 
6402: 837:         804 LOAD_CONST           ("contents")
6403:              806 LOAD_CONST           ("parts")
6404:              808 LOAD_CONST           ("text")
6405:              810 LOAD_FAST            (system_prompt)
6406:              812 BUILD_MAP            1
6407:              814 BUILD_LIST           1
6408:              816 BUILD_MAP            1
6409:              818 BUILD_LIST           1
6410: 
6411: 836:         820 BUILD_MAP            1
6412:              822 STORE_FAST           (payload)
6413: 
6414: 839:         824 LOAD_FAST            (requests)
6415:              826 LOAD_ATTR            (NULL|self + post)
6416:              846 LOAD_FAST            (url_api)
6417:              848 LOAD_FAST            (payload)
6418:              850 LOAD_CONST           (8)
6419:              852 KW_NAMES             (('json', 'timeout'))
6420:              854 CALL                 3
6421:              862 STORE_FAST           (res)
6422: 
6423: 840:         864 LOAD_FAST            (res)
6424:              866 LOAD_ATTR            (status_code)
6425:              886 LOAD_CONST           (200)
6426:              888 COMPARE_OP           (==)
6427:              892 POP_JUMP_IF_FALSE    (to 1008)
6428: 
6429: 841:         894 LOAD_FAST            (res)
6430:              896 LOAD_ATTR            (NULL|self + json)
6431:              916 CALL                 0
6432:              924 LOAD_CONST           ("candidates")
6433:              926 BINARY_SUBSCR
6434:              930 LOAD_CONST           (0)
6435:              932 BINARY_SUBSCR
6436:              936 LOAD_CONST           ("content")
6437:              938 BINARY_SUBSCR
6438:              942 LOAD_CONST           ("parts")
6439:              944 BINARY_SUBSCR
6440:              948 LOAD_CONST           (0)
6441:              950 BINARY_SUBSCR
6442:              954 LOAD_CONST           ("text")
6443:              956 BINARY_SUBSCR
6444:              960 STORE_FAST           (text_response)
6445: 
6446: 842:         962 LOAD_GLOBAL          (NULL + response)
6447:              972 LOAD_ATTR            (Response)
6448:              992 LOAD_CONST           ("resposta")
6449:              994 LOAD_FAST            (text_response)
6450:              996 BUILD_MAP            1
6451:              998 CALL                 1
6452:             1006 RETURN_VALUE
6453: 
6454: 840:     >> 1008 JUMP_FORWARD         (to 1246)
6455: 
6456: 846:     >> 1010 LOAD_FAST            (openai_key)
6457:             1012 POP_JUMP_IF_FALSE    (to 1246)
6458: 
6459: 847:        1014 LOAD_CONST           (0)
6460:             1016 LOAD_CONST           (None)
6461:             1018 IMPORT_NAME          (requests)
6462:             1020 STORE_FAST           (requests)
6463: 
6464: 848:        1022 NOP
6465: 
6466: 849:        1024 LOAD_CONST           ("https://api.openai.com/v1/chat/completions")
6467:             1026 STORE_FAST           (url_api)
6468: 
6469: 851:        1028 LOAD_CONST           ("Bearer ")
6470:             1030 LOAD_FAST            (openai_key)
6471:             1032 FORMAT_VALUE         0
6472:             1034 BUILD_STRING         2
6473: 
6474: 852:        1036 LOAD_CONST           ("application/json")
6475: 
6476: 850:        1038 LOAD_CONST           (('Authorization', 'Content-Type'))
6477:             1040 BUILD_CONST_KEY_MAP  2
6478:             1042 STORE_FAST           (headers)
6479: 
6480: 855:        1044 LOAD_CONST           ("gpt-4o-mini")
6481: 
6482: 857:        1046 LOAD_CONST           ("system")
6483:             1048 LOAD_CONST           ("VocÛ Ú o Assistente Executivo de InteligÛncia AnalÝtica do Hospital.")
6484:             1050 LOAD_CONST           (('role', 'content'))
6485:             1052 BUILD_CONST_KEY_MAP  2
6486: 
6487: 858:        1054 LOAD_CONST           ("user")
6488:             1056 LOAD_FAST            (system_prompt)
6489:             1058 LOAD_CONST           (('role', 'content'))
6490:             1060 BUILD_CONST_KEY_MAP  2
6491: 
6492: 856:        1062 BUILD_LIST           2
6493: 
6494: 854:        1064 LOAD_CONST           (('model', 'messages'))
6495:             1066 BUILD_CONST_KEY_MAP  2
6496:             1068 STORE_FAST           (payload)
6497: 
6498: 861:        1070 LOAD_FAST            (requests)
6499:             1072 LOAD_ATTR            (NULL|self + post)
6500:             1092 LOAD_FAST            (url_api)
6501:             1094 LOAD_FAST            (payload)
6502:             1096 LOAD_FAST            (headers)
6503:             1098 LOAD_CONST           (8)
6504:             1100 KW_NAMES             (('json', 'headers', 'timeout'))
6505:             1102 CALL                 4
6506:             1110 STORE_FAST           (res)
6507: 
6508: 862:        1112 LOAD_FAST            (res)
6509:             1114 LOAD_ATTR            (status_code)
6510:             1134 LOAD_CONST           (200)
6511:             1136 COMPARE_OP           (==)
6512:             1140 POP_JUMP_IF_FALSE    (to 1244)
6513: 
6514: 863:        1142 LOAD_FAST            (res)
6515:             1144 LOAD_ATTR            (NULL|self + json)
6516:             1164 CALL                 0
6517:             1172 LOAD_CONST           ("choices")
6518:             1174 BINARY_SUBSCR
6519:             1178 LOAD_CONST           (0)
6520:             1180 BINARY_SUBSCR
6521:             1184 LOAD_CONST           ("message")
6522:             1186 BINARY_SUBSCR
6523:             1190 LOAD_CONST           ("content")
6524:             1192 BINARY_SUBSCR
6525:             1196 STORE_FAST           (text_response)
6526: 
6527: 864:        1198 LOAD_GLOBAL          (NULL + response)
6528:             1208 LOAD_ATTR            (Response)
6529:             1228 LOAD_CONST           ("resposta")
6530:             1230 LOAD_FAST            (text_response)
6531:             1232 BUILD_MAP            1
6532:             1234 CALL                 1
6533:             1242 RETURN_VALUE
6534: 
6535: 862:     >> 1244 NOP
6536: 
6537: 868:     >> 1246 LOAD_CONST           (0)
6538:             1248 LOAD_CONST           (None)
6539:             1250 IMPORT_NAME          (re)
6540:             1252 STORE_FAST           (re)
6541: 
6542: 869:        1254 LOAD_CONST           (0.0)
6543:             1256 STORE_FAST           (val_num)
6544: 
6545: 870:        1258 BUILD_MAP            0
6546: 
6547: 871:        1260 LOAD_CONST           ("faturamento")
6548:             1262 LOAD_CONST           ("O **Faturamento SUS** mede o montante financeiro total faturado e homologado sob o regime do SUS no perÝodo. ╔ crÝtico para a sa·de financeira do hospital, pois o SUS representa uma fatia importante da receita operacional, exigindo o controle estrito das AIHs e APACs para evitar glosas administrativas.")
6549: 
6550: 870:        1264 MAP_ADD              1
6551: 
6552: 872:        1266 LOAD_CONST           ("gestao de glosas")
6553:             1268 LOAD_CONST           ("A **GestÒo de Glosas** avalia o andamento das faturas contestadas e o status de recuperaþÒo das glosas aplicadas pelos convÛnios, identificando a eficiÛncia operacional das ßreas de auditoria e faturamento.")
6554: 
6555: 870:        1270 MAP_ADD              1
6556: 
6557: 873:        1272 LOAD_CONST           ("glosa")
6558:             1274 LOAD_CONST           ("O **═ndice de Glosa Inicial** mede o percentual do faturamento total que foi inicialmente rejeitado pelas operadoras ou pelo gestor do SUS devido a inconsistÛncias cadastrais, falhas de autorizaþÒo de contas mÚdicas ou falta de conformidade clÝnica.")
6559: 
6560: 870:        1276 MAP_ADD              1
6561: 
6562: 874:        1278 LOAD_CONST           ("recupera")
6563:             1280 LOAD_CONST           ("A **Taxa de RecuperaþÒo** avalia a eficiÛncia e agilidade da equipe de auditoria e faturamento em contestar e recuperar recursos inicialmente glosados pelas operadoras ou pelo gestor p·blico, minimizando o impacto no fluxo de caixa.")
6564: 
6565: 870:        1282 MAP_ADD              1
6566: 
6567: 875:        1284 LOAD_CONST           ("evas")
6568:             1286 LOAD_CONST           ("A **EvasÒo de Receita** representa as perdas financeiras definitivas decorrentes de glosas nÒo recuperadas no perÝodo. ╔ um indicador vital que impacta diretamente a margem EBITDA e a capacidade de investimento da instituiþÒo.")
6569: 
6570: 870:        1288 MAP_ADD              1
6571: 
6572: 876:        1290 LOAD_CONST           ("backlog")
6573:             1292 LOAD_CONST           ("A **Fila de Espera (Backlog)** quantifica o total de pacientes com exames ou cirurgias programadas que se encontram em status 'Agendado' aguardando execuþÒo fÝsica, indicando a pressÒo assistencial do fluxo do AGHUse.")
6574: 
6575: 870:        1294 MAP_ADD              1
6576: 
6577: 877:        1296 LOAD_CONST           ("fila")
6578:             1298 LOAD_CONST           ("A **Fila de Espera (Backlog)** quantifica o total de pacientes com exames ou cirurgias programadas que se encontram em status 'Agendado' aguardando execuþÒo fÝsica, indicando a pressÒo assistencial do fluxo do AGHUse.")
6579: 
6580: 870:        1300 MAP_ADD              1
6581: 
6582: 878:        1302 LOAD_CONST           ("ocupa")
6583:             1304 LOAD_CONST           ("A **Taxa de OcupaþÒo MÚdia** mede o percentual mÚdio de leitos ou cadeiras ocupados em relaþÒo Ó capacidade mßxima. Ela avalia o aproveitamento dos recursos fÝsicos e Ú fundamental para gerenciar o gargalo de admiss§es hospitalares.")
6584: 
6585: 870:        1306 MAP_ADD              1
6586: 
6587: 879:        1308 LOAD_CONST           ("suspen")
6588:             1310 LOAD_CONST           ("A **Taxa de SuspensÒo de Procedimentos** monitora a proporþÒo de cirurgias ou exames cancelados ap¾s o agendamento oficial. Reflete falhas no preparo clÝnico prÚ-operat¾rio dos pacientes ou na coordenaþÒo das salas de cirurgia.")
6589: 
6590: 870:        1312 MAP_ADD              1
6591: 
6592: 880:        1314 LOAD_CONST           ("tmp")
6593:             1316 LOAD_CONST           ("O **Tempo MÚdio de PermanÛncia (TMP)** monitora o n·mero mÚdio de dias que os pacientes passam internados. ╔ um indicador da eficiÛncia clÝnica, no qual permanÛncias prolongadas aumentam os custos fixos e os riscos de infecþÒo.")
6594: 
6595: 870:        1318 MAP_ADD              1
6596: 
6597: 881:        1320 LOAD_CONST           ("densidade")
6598:             1322 LOAD_CONST           ("A **Densidade de Recursos Humanos** mede a proporþÒo mÚdia de profissionais assistenciais (como enfermeiros e tÚcnicos) ativos por leito instalado, sendo uma mÚtrica chave de seguranþa do paciente contra fadiga e sobrecarga.")
6599: 
6600: 870:        1324 MAP_ADD              1
6601: 
6602: 882:        1326 LOAD_CONST           ("risco")
6603:             1328 LOAD_CONST           ("O **Score de Risco ClÝnico** Ú uma mÚtrica preditiva que unifica absenteÝsmo mÚdico, densidade de RH, e ocorrÛncias de erros/infecþ§es por setor para sinalizar preventivamente quais ßreas necessitam de intervenþÒo urgente.")
6604: 
6605: 870:        1330 MAP_ADD              1
6606: 
6607: 883:        1332 LOAD_CONST           ("iras")
6608:             1334 LOAD_CONST           ("A **Taxa IRAS** avalia o percentual de Infecþ§es Relacionadas Ó AssistÛncia Ó Sa·de sobre o total de saÝdas, funcionando como o principal term¶metro de conformidade e seguranþa higiÛnica e clÝnica da instituiþÒo.")
6609: 
6610: 870:        1336 MAP_ADD              1
6611: 
6612: 884:        1338 LOAD_CONST           ("substitui")
6613:             1340 LOAD_CONST           ("O tempo de **SubstituiþÒo de Leito** monitora o intervalo entre a desocupaþÒo do leito por alta e a sua disponibilidade real para o pr¾ximo paciente, medindo a eficiÛncia operacional da hotelaria.")
6614: 
6615: 870:        1342 MAP_ADD              1
6616: 
6617: 885:        1344 LOAD_CONST           ("nps")
6618:             1346 LOAD_CONST           ("O **NPS (Net Promoter Score)** mede a satisfaþÒo e fidelidade do paciente ap¾s o atendimento hospitalar, indicando a percepþÒo humana sobre o cuidado recebido e a experiÛncia geral na instituiþÒo.")
6619: 
6620: 870:        1348 MAP_ADD              1
6621: 
6622: 886:        1350 LOAD_CONST           ("reinterna")
6623:             1352 LOAD_CONST           ("A **Taxa de ReinternaþÒo** monitora o percentual de pacientes que voltam a ser hospitalizados em atÚ 30 dias pela mesma causa. Altos Ýndices apontam para problemas na eficßcia do tratamento ou na qualidade do processo de alta.")
6624: 
6625: 870:        1354 MAP_ADD              1
6626: 
6627: 887:        1356 LOAD_CONST           ("consumo")
6628:             1358 LOAD_CONST           ("O **Consumo ┴gua/Energia** monitora a eficiÛncia ecol¾gica e financeira da infraestrutura hospitalar, visando otimizar custos operacionais de ßgua e energia elÚtrica sem comprometer a operaþÒo e seguranþa clÝnica.")
6629: 
6630: 870:        1360 MAP_ADD              1
6631: 
6632: 888:        1362 LOAD_CONST           ("O **Giro de Estoque** monitora a frequÛncia com que o estoque de medicamentos da farmßcia central se renova. Altos giros indicam boa gestÒo de capital de giro, enquanto baixos giros sugerem excesso de itens parados e risco de vencimento.")
6633: 
6634: 889:        1364 LOAD_CONST           ("O **Giro de Sala** mede a duraþÒo mÚdia de ocupaþÒo das salas cir·rgicas, englobando o setup de anestesia, o tempo cir·rgico e o intervalo de limpeza fÝsica da sala pela enfermagem.")
6635: 
6636: 890:        1366 LOAD_CONST           ("O **Giro de Estoque** monitora a frequÛncia com que o estoque de medicamentos da farmßcia central se renova. Altos giros indicam boa gestÒo de capital de giro, enquanto baixos giros sugerem excesso de itens parados e risco de vencimento.")
6637: 
6638: 891:        1368 LOAD_CONST           ("O **Custo Total** de medicamentos monitora o consumo financeiro acumulado das dispensaþ§es da farmßcia, servindo de term¶metro para controle do orþamento de insumos da instituiþÒo.")
6639: 
6640: 892:        1370 LOAD_CONST           ("O indicador de **Erros MedicaþÒo** monitora incidentes na prescriþÒo, dispensaþÒo ou administraþÒo de medicamentos, servindo como term¶metro primßrio de seguranþa assistencial nas unidades.")
6641: 
6642: 893:        1372 LOAD_CONST           ("A **Ruptura Estoque** mede a ocorrÛncia de falta de itens assistenciais crÝticos na farmßcia quando solicitados pelas equipes. Altos Ýndices indicam falhas de suprimentos que comprometem diretamente a assistÛncia.")
6643: 
6644: 894:        1374 LOAD_CONST           ("A **AdesÒo Protocolos** clÝnicos avalia a conformidade das condutas mÚdicas em relaþÒo Ós diretrizes oficiais adotadas no hospital (como os protocolos de Sepse e AVC), assegurando um cuidado homogÛneo e seguro.")
6645: 
6646: 895:        1376 LOAD_CONST           ("O **Tempo Prontußrio** mede a mÚdia de minutos ou horas que os mÚdicos levam para fechar o prontußrio do paciente ap¾s o atendimento. Fechamentos tardios atrasam o faturamento da conta do SUS e operadoras.")
6647: 
6648: 896:        1378 LOAD_CONST           ("O **AbsenteÝsmo MÚdico** monitora o Ýndice de faltas e atrasos na escala de plant§es, refletindo o grau de aderÛncia dos profissionais Ós escalas fÝsicas homologadas.")
6649: 
6650: 897:        1380 LOAD_CONST           ("O **Ticket MÚdio** avalia o valor financeiro mÚdio faturado por atendimento ou internaþÒo, auxiliando a gerÛncia na anßlise da complexidade dos casos assistidos no hospital.")
6651: 
6652: 898:        1382 LOAD_CONST           ("O **PMR (Prazo MÚdio de Recebimento)** monitora o intervalo de dias entre a alta clÝnica do paciente e o efetivo pagamento da conta faturada pelos convÛnios e SUS.")
6653: 
6654: 899:        1384 LOAD_CONST           ("O **EBITDA Operacional** mede a lucratividade operacional do hospital antes de juros, impostos, depreciaþÒo e amortizaþÒo, demonstrando a capacidade de geraþÒo de caixa das atividades essenciais.")
6655: 
6656: 900:        1386 LOAD_CONST           ("O **Volume Especialidade** quantifica a distribuiþÒo dos atendimentos e procedimentos por especialidade mÚdica, servindo para planejar a escala mÚdica e a capacidade instalada.")
6657: 
6658: 901:        1388 LOAD_CONST           ("A **Produtividade por Equipamento** mede o volume de procedimentos e exames diagn¾sticos realizados nas mßquinas de alta complexidade mÚdica, otimizando o uso dos ativos.")
6659: 
6660: 902:        1390 LOAD_CONST           ("A **Taxa ConversÒo** indica a proporþÒo de cirurgias ou procedimentos de fato realizados em relaþÒo aos agendamentos solicitados, auxiliando a reduzir suspens§es e ociosidade de equipes.")
6661: 
6662: 870:        1392 LOAD_CONST           (('giro de estoque', 'giro de sala', 'giro', 'custo', 'erro', 'ruptura', 'ades', 'prontu', 'absen', 'ticket', 'pmr', 'ebitda', 'volume', 'produtividade', 'conversao'))
6663:             1394 BUILD_CONST_KEY_MAP  15
6664:             1396 DICT_UPDATE          1
6665:             1398 STORE_FAST           (p1_concepts)
6666: 
6667: 905:        1400 BUILD_MAP            0
6668: 
6669: 906:        1402 LOAD_CONST           ("faturamento")
6670:             1404 LOAD_CONST           ("O valor atual de **{valor_atual}** na unidade **{unidade}** indica a receita processada. Sugere-se intensificar a auditoria preventiva em contas de alta complexidade (como cirurgias) antes do fechamento do lote para assegurar conformidade total e evitar prejuÝzos.")
6671: 
6672: 905:        1406 MAP_ADD              1
6673: 
6674: 907:        1408 LOAD_CONST           ("gestao de glosas")
6675:             1410 LOAD_CONST           ("O andamento da gestÒo de glosas de **{valor_atual}** na unidade **{unidade}** aponta para oportunidades de conciliaþÒo. Sugere-se priorizar recursos junto Ós maiores operadoras parceiras e padronizar justificativas clÝnicas.")
6676: 
6677: 905:        1412 MAP_ADD              1
6678: 
6679: 908:        1414 LOAD_CONST           ("glosa")
6680:             1416 LOAD_CONST           ("O Ýndice atual de **{valor_atual}** na unidade **{unidade}** estß em patamar considerßvel. Recomenda-se realizar um treinamento com a recepþÒo para reduzir erros cadastrais e revisar o fluxo de prÚ-autorizaþ§es junto Ós operadoras.")
6681: 
6682: 905:        1418 MAP_ADD              1
6683: 
6684: 909:        1420 LOAD_CONST           ("recupera")
6685:             1422 LOAD_CONST           ("A taxa de recuperaþÒo de **{valor_atual}** na unidade **{unidade}** reflete a eficßcia dos recursos. Para maximizar esse indicador, sugere-se a padronizaþÒo das justificativas clÝnicas e a automatizaþÒo da conciliaþÒo de glosas.")
6686: 
6687: 905:        1424 MAP_ADD              1
6688: 
6689: 910:        1426 LOAD_CONST           ("evas")
6690:             1428 LOAD_CONST           ("O valor de **{valor_atual}** na unidade **{unidade}** representa perda de receita definitiva. Alerta-se a gestÒo para implementar travas no prontußrio eletr¶nico que impeþam a alta administrativa sem que todas as guias de cobranþa estejam validadas.")
6691: 
6692: 905:        1430 MAP_ADD              1
6693: 
6694: 911:        1432 LOAD_CONST           ("backlog")
6695:             1434 LOAD_CONST           ("A fila atual de **{valor_atual}** na unidade **{unidade}** representa um gargalo. Recomenda-se otimizar a escala das salas de cirurgia/exames e priorizar procedimentos que dependam de equipamentos com maior ociosidade operacional.")
6696: 
6697: 905:        1436 MAP_ADD              1
6698: 
6699: 912:        1438 LOAD_CONST           ("fila")
6700:             1440 LOAD_CONST           ("A fila atual de **{valor_atual}** na unidade **{unidade}** representa um gargalo. Recomenda-se otimizar a escala das salas de cirurgia/exames e priorizar procedimentos que dependam de equipamentos com maior ociosidade operacional.")
6701: 
6702: 905:        1442 MAP_ADD              1
6703: 
6704: 913:        1444 LOAD_CONST           ("ocupa")
6705:             1446 LOAD_CONST           ("A ocupaþÒo atual de **{valor_atual}** na unidade **{unidade}** estß pr¾xima da saturaþÒo. Recomenda-se agilizar as altas seguras pela manhÒ e implantar um painel de monitoramento do giro de leitos para diminuir o tempo de espera no pronto-socorro.")
6706: 
6707: 905:        1448 MAP_ADD              1
6708: 
6709: 914:        1450 LOAD_CONST           ("suspen")
6710:             1452 LOAD_CONST           ("A taxa de suspensÒo de **{valor_atual}** na unidade **{unidade}** Ú crÝtica. Sugere-se implementar um contato telef¶nico de confirmaþÒo com o paciente 24h antes do procedimento para garantir o preparo prÚ-operat¾rio adequado e reduzir absenteÝsmo.")
6711: 
6712: 905:        1454 MAP_ADD              1
6713: 
6714: 915:        1456 LOAD_CONST           ("tmp")
6715:             1458 LOAD_CONST           ("O TMP atual de **{valor_atual}** na unidade **{unidade}** exige atenþÒo. Recomenda-se auditar casos de longa permanÛncia (acima de 15 dias) e criar uma comissÒo multidisciplinar para agilizar desospitalizaþ§es seguras.")
6716: 
6717: 905:        1460 MAP_ADD              1
6718: 
6719: 916:        1462 LOAD_CONST           ("densidade")
6720:             1464 LOAD_CONST           ("A densidade atual de **{valor_atual}** na unidade **{unidade}** aponta para sobrecarga de pessoal. Recomenda-se remanejar tÚcnicos e enfermeiros temporariamente para este setor para evitar a fadiga da equipe e mitigar o risco de erros assistenciais.")
6721: 
6722: 905:        1466 MAP_ADD              1
6723: 
6724: 917:        1468 LOAD_CONST           ("risco")
6725:             1470 LOAD_CONST           ("O score atual de **{valor_atual}** na unidade **{unidade}** Ú classificado como crÝtico. Recomenda-se intervenþÒo preventiva imediata da lideranþa com auditoria volante e redimensionamento imediato das escalas de pessoal assistencial no setor.")
6726: 
6727: 905:        1472 MAP_ADD              1
6728: 
6729: 918:        1474 LOAD_CONST           ("iras")
6730:             1476 LOAD_CONST           ("A taxa de infecþ§es de **{valor_atual}** na unidade **{unidade}** demanda reforþo. Sugere-se intensificar a fiscalizaþÒo da lavagem de mÒos e auditar o cumprimento estrito das rotinas de desinfecþÒo de leitos da hotelaria.")
6731: 
6732: 905:        1478 MAP_ADD              1
6733: 
6734: 919:        1480 LOAD_CONST           ("substitui")
6735:             1482 LOAD_CONST           ("O tempo atual de **{valor_atual}** na unidade **{unidade}** estß acima do ideal (120 min). Recomenda-se criar alertas em tempo real para a equipe de limpeza assim que o paciente desocupe o leito, agilizando o fluxo.")
6736: 
6737: 905:        1484 MAP_ADD              1
6738: 
6739: 920:        1486 LOAD_CONST           ("nps")
6740:             1488 LOAD_CONST           ("O NPS atual de **{valor_atual}** reflete a experiÛncia do paciente. Recomenda-se mapear os principais detratores atravÚs de ligaþ§es p¾s-alta e agir nos gargalos de hotelaria e alimentaþÒo relatados.")
6741: 
6742: 905:        1490 MAP_ADD              1
6743: 
6744: 921:        1492 LOAD_CONST           ("reinterna")
6745:             1494 LOAD_CONST           ("A taxa de reinternaþÒo atual de **{valor_atual}** na unidade **{unidade}** exige revisÒo. Sugere-se implantar um acompanhamento telef¶nico p¾s-alta de 48 horas para tirar d·vidas de prescriþÒo e mitigar retornos evitßveis.")
6746: 
6747: 905:        1496 MAP_ADD              1
6748: 
6749: 922:        1498 LOAD_CONST           ("consumo")
6750:             1500 LOAD_CONST           ("O consumo registrado de **{valor_atual}** na unidade **{unidade}** indica o nÝvel de utilizaþÒo de recursos prediais. Recomenda-se realizar uma auditoria de desperdÝcio e checar contratos de demanda de energia para otimizar os custos fixos.")
6751: 
6752: 905:        1502 MAP_ADD              1
6753: 
6754: 923:        1504 LOAD_CONST           ("O giro atual de **{valor_atual}** na unidade **{unidade}** aponta para a velocidade de escoamento. Recomenda-se ajustar a curva ABC de compras e calibrar os estoques mÝnimos de medicamentos de alto custo para evitar vencimentos.")
6755: 
6756: 924:        1506 LOAD_CONST           ("O giro de sala atual de **{valor_atual}** na unidade **{unidade}** exige otimizaþÒo. Recomenda-se paralelizar a limpeza fÝsica com o preparo anestÚsico da pr¾xima cirurgia em sala contÝgua para reduzir a ociosidade do bloco.")
6757: 
6758: 925:        1508 LOAD_CONST           ("O giro atual de **{valor_atual}** na unidade **{unidade}** aponta para a velocidade de escoamento. Recomenda-se ajustar a curva ABC de compras e calibrar os estoques mÝnimos de medicamentos de alto custo para evitar vencimentos.")
6759: 
6760: 926:        1510 LOAD_CONST           ("O custo total acumulado de **{valor_atual}** na unidade **{unidade}** exige conciliaþÒo orþamentßria. Recomenda-se auditar prescriþ§es de alta variabilidade clÝnica e padronizar o uso de genÚricos de alta eficßcia.")
6761: 
6762: 927:        1512 LOAD_CONST           ("O volume atual de **{valor_atual}** erros de medicaþÒo na unidade **{unidade}** exige revisÒo imediata. Recomenda-se reforþar a dupla checagem na enfermagem e revisar a clareza da prescriþÒo no prontußrio eletr¶nico.")
6763: 
6764: 928:        1514 LOAD_CONST           ("A taxa de ruptura de **{valor_atual}** na unidade **{unidade}** estß elevada. Sugere-se adiantar os pedidos de compra junto aos fornecedores homologados e verificar eventuais atrasos logÝsticos na entrega.")
6765: 
6766: 929:        1516 LOAD_CONST           ("A taxa de adesÒo atual de **{valor_atual}** na unidade **{unidade}** indica a conformidade clÝnica. Sugere-se promover sess§es de educaþÒo continuada com a equipe mÚdica e simplificar as ferramentas de registro no sistema.")
6767: 
6768: 930:        1518 LOAD_CONST           ("O tempo de fechamento de **{valor_atual}** na unidade **{unidade}** estß acima do ideal. Recomenda-se disparar alertas automßticos aos mÚdicos com pendÛncias acima de 24 horas para evitar glosas por perda de prazo.")
6769: 
6770: 931:        1520 LOAD_CONST           ("O absenteÝsmo atual de **{valor_atual}** na unidade **{unidade}** estß crÝtico. Recomenda-se acionar o banco de mÚdicos de reserva para cobrir escalas e realizar entrevista de feedback com os profissionais com maior recorrÛncia de faltas.")
6771: 
6772: 932:        1522 LOAD_CONST           ("O ticket mÚdio atual de **{valor_atual}** na unidade **{unidade}** reflete a receita por paciente. Sugere-se auditar o registro correto de procedimentos nas contas para garantir que todo o cuidado prestado esteja sendo faturado.")
6773: 
6774: 933:        1524 LOAD_CONST           ("O PMR atual de **{valor_atual}** na unidade **{unidade}** impacta o fluxo de caixa. Recomenda-se revisar as glosas recursais pendentes e estreitar a negociaþÒo com as operadoras para acelerar o ciclo de contas a receber.")
6775: 
6776: 934:        1526 LOAD_CONST           ("O EBITDA operacional atual de **{valor_atual}** na unidade **{unidade}** indica a capacidade de autofinanciamento. Sugere-se revisar os custos operacionais de insumos farmacol¾gicos e taxa de glosa para melhorar a margem operacional lÝquida.")
6777: 
6778: 935:        1528 LOAD_CONST           ("O volume assistencial atual de **{valor_atual}** na unidade **{unidade}** deve ser avaliado contra a capacidade instalada. Recomenda-se redimensionar escalas mÚdicas para especialidades com maior tempo mÚdio de fila.")
6779: 
6780: 936:        1530 LOAD_CONST           ("A produtividade registrada de **{valor_atual}** na unidade **{unidade}** exige anßlise de ociosidade tÚcnica. Sugere-se agendar exames eletivos em horßrios alternativos para otimizar o retorno operacional do ativo fÝsico.")
6781: 
6782: 937:        1532 LOAD_CONST           ("A taxa de conversÒo atual de **{valor_atual}** na unidade **{unidade}** indica a estabilidade da agenda. Recomenda-se implantar check-in cir·rgico digital 48h antes e revisar os tempos de liberaþÒo de leitos cir·rgicos.")
6783: 
6784: 905:        1534 LOAD_CONST           (('giro de estoque', 'giro de sala', 'giro', 'custo', 'erro', 'ruptura', 'ades', 'prontu', 'absen', 'ticket', 'pmr', 'ebitda', 'volume', 'produtividade', 'conversao'))
6785:             1536 BUILD_CONST_KEY_MAP  15
6786:             1538 DICT_UPDATE          1
6787:             1540 STORE_FAST           (p2_actions)
6788: 
6789: 941:        1542 LOAD_CONST           ("faturamento")
6790:             1544 STORE_FAST           (key_match)
6791: 
6792: 942:        1546 LOAD_GLOBAL          (NULL + sorted)
6793:             1556 LOAD_FAST            (p1_concepts)
6794:             1558 LOAD_ATTR            (NULL|self + keys)
6795:             1578 CALL                 0
6796:             1586 LOAD_CLOSURE         (normalize_text)
6797:             1588 BUILD_TUPLE          1
6798:             1590 LOAD_CONST           (<Code311 code object <lambda> at 0x1f2950bc9e0, file indicadores\views.py>, line 942)
6799:             1592 MAKE_FUNCTION        (closure)
6800:             1594 LOAD_CONST           (True)
6801:             1596 KW_NAMES             (('key', 'reverse'))
6802:             1598 CALL                 3
6803:             1606 STORE_FAST           (sorted_keys)
6804: 
6805: 943:        1608 LOAD_FAST            (sorted_keys)
6806:             1610 GET_ITER
6807:             1612 FOR_ITER             (to 1660)
6808:             1616 STORE_FAST           (k)
6809: 
6810: 944:        1618 PUSH_NULL
6811:             1620 LOAD_DEREF           (normalize_text)
6812:             1622 LOAD_FAST            (k)
6813:             1624 CALL                 1
6814:             1632 STORE_FAST           (k_norm)
6815: 
6816: 945:        1634 LOAD_FAST            (k_norm)
6817:             1636 LOAD_FAST            (indicador_norm)
6818:             1638 CONTAINS_OP          (in)
6819:             1640 POP_JUMP_IF_TRUE     (to 1652)
6820:             1642 LOAD_FAST            (indicador_norm)
6821:             1644 LOAD_FAST            (k_norm)
6822:             1646 CONTAINS_OP          (in)
6823:             1648 POP_JUMP_IF_TRUE     (to 1652)
6824:             1650 JUMP_BACKWARD        (to 1612)
6825: 
6826: 946:     >> 1652 LOAD_FAST            (k)
6827:             1654 STORE_FAST           (key_match)
6828: 
6829: 947:        1656 POP_TOP
6830:          >> 1658 JUMP_FORWARD         (to 1662)
6831: 
6832: 943:        1660 END_FOR
6833: 
6834: 949:     >> 1662 LOAD_FAST            (p1_concepts)
6835:             1664 LOAD_ATTR            (NULL|self + get)
6836:             1684 LOAD_FAST            (key_match)
6837:             1686 LOAD_FAST            (p1_concepts)
6838:             1688 LOAD_CONST           ("faturamento")
6839:             1690 BINARY_SUBSCR
6840:             1694 CALL                 2
6841:             1702 STORE_FAST           (concept_p)
6842: 
6843: 950:        1704 LOAD_FAST            (p2_actions)
6844:             1706 LOAD_ATTR            (NULL|self + get)
6845:             1726 LOAD_FAST            (key_match)
6846:             1728 LOAD_FAST            (p2_actions)
6847:             1730 LOAD_CONST           ("faturamento")
6848:             1732 BINARY_SUBSCR
6849:             1736 CALL                 2
6850:             1744 LOAD_ATTR            (NULL|self + format)
6851: 
6852: 951:        1764 LOAD_FAST            (valor_atual)
6853: 
6854: 952:        1766 LOAD_FAST            (unidade)
6855: 
6856: 950:        1768 KW_NAMES             (('valor_atual', 'unidade'))
6857:             1770 CALL                 2
6858:             1778 STORE_FAST           (action_p)
6859: 
6860: 955:        1780 LOAD_CONST           ("### **[Conceito]**\n")
6861:             1782 LOAD_FAST            (concept_p)
6862:             1784 FORMAT_VALUE         0
6863:             1786 LOAD_CONST           ("\n\n### **[Anßlise de AþÒo]**\n")
6864:             1788 LOAD_FAST            (action_p)
6865:             1790 FORMAT_VALUE         0
6866:             1792 BUILD_STRING         4
6867:             1794 STORE_FAST           (response_markdown)
6868: 
6869: 957:        1796 LOAD_GLOBAL          (NULL + response)
6870:             1806 LOAD_ATTR            (Response)
6871:             1826 LOAD_CONST           ("resposta")
6872:             1828 LOAD_FAST            (response_markdown)
6873:             1830 BUILD_MAP            1
6874:             1832 CALL                 1
6875:             1840 RETURN_VALUE
6876:             1842 PUSH_EXC_INFO
6877: 
6878: 843:        1844 LOAD_GLOBAL          (Exception)
6879:             1854 CHECK_EXC_MATCH
6880:             1856 POP_JUMP_IF_FALSE    (to 1866)
6881:             1858 POP_TOP
6882: 
6883: 844:        1860 POP_EXCEPT
6884:             1862 EXTENDED_ARG         (256)
6885:             1864 JUMP_BACKWARD        (to 1246)
6886: 
6887: 843:     >> 1866 RERAISE              0
6888:             1868 COPY                 3
6889:             1870 POP_EXCEPT
6890:             1872 RERAISE              1
6891:             1874 PUSH_EXC_INFO
6892: 
6893: 865:        1876 LOAD_GLOBAL          (Exception)
6894:             1886 CHECK_EXC_MATCH
6895:             1888 POP_JUMP_IF_FALSE    (to 1898)
6896:             1890 POP_TOP
6897: 
6898: 866:        1892 POP_EXCEPT
6899:             1894 EXTENDED_ARG         (256)
6900:             1896 JUMP_BACKWARD        (to 1246)
6901: 
6902: 865:     >> 1898 RERAISE              0
6903:             1900 COPY                 3
6904:             1902 POP_EXCEPT
6905:             1904 RERAISE              1
6906: 
6907: ExceptionTable:
6908:   794 to 1004 -> 1842 [0]
6909:   1024 to 1240 -> 1874 [0]
